machbaseAPI/__init__.py
machbaseAPI/libmachbaseAPI.so
machbaseAPI/machbaseAPI.py
testmhdbAPI/__init__.py
testmhdbAPI/libmachbaseAPI.so
testmhdbAPI/machbaseAPI.py
testmhdbAPI-1.9.dist-info/METADATA
testmhdbAPI-1.9.dist-info/WHEEL
testmhdbAPI-1.9.dist-info/top_level.txt
testmhdbAPI-1.9.dist-info/RECORD
