Metadata-Version: 2.1
Name: testmhdbAPI
Version: 1.9
Summary: Machbase-Python3-API
Home-page: http://www.machbase.com
Author: machbase
Author-email: support@machbase.com
License: UNKNOWN
Platform: LINUX
